{
  "project_info": {
    "project_number": "523332738118",
    "project_id": "flutter-firebase-app-8c7e5",
    "storage_bucket": "flutter-firebase-app-8c7e5.appspot.com"
  },
  "client": [
    {
      "client_info": {
        "mobilesdk_app_id": "1:523332738118:android:9eb4feab93a9c398293e47",
        "android_client_info": {
          "package_name": "com.example.demo1"
        }
      },
      "oauth_client": [],
      "api_key": [
        {
          "current_key": "AIzaSyB6VX-m6ph5NzS5pYSQcBJfTsZ02rSSoN8"
        }
      ],
      "services": {
        "appinvite_service": {
          "other_platform_oauth_client": []
        }
      }
    }
  ],
  "configuration_version": "1"
}